kps/__init__.py
kps/__main__.py
kps/kps.py
kps/test_kps.py
kps-1.0.0.dist-info/METADATA
kps-1.0.0.dist-info/WHEEL
kps-1.0.0.dist-info/entry_points.txt
kps-1.0.0.dist-info/top_level.txt
kps-1.0.0.dist-info/RECORD
